climate_toolbox/__init__.py
climate_toolbox/climate_toolbox.py
climate_toolbox-0.1.5.dist-info/AUTHORS.rst
climate_toolbox-0.1.5.dist-info/LICENSE
climate_toolbox-0.1.5.dist-info/METADATA
climate_toolbox-0.1.5.dist-info/WHEEL
climate_toolbox-0.1.5.dist-info/entry_points.txt
climate_toolbox-0.1.5.dist-info/top_level.txt
climate_toolbox-0.1.5.dist-info/RECORD
