Metadata-Version: 2.1
Name: climate-toolbox
Version: 0.1.5
Summary: Tools for climate data wrangling
Home-page: https://github.com/ClimateImpactLab/climate_toolbox
Author: Justin Simcock
Author-email: jsimcock@rhg.com
License: MIT license
Keywords: climate_toolbox
Platform: UNKNOWN
Classifier: Development Status :: 2 - Pre-Alpha
Classifier: Intended Audience :: Developers
Classifier: License :: OSI Approved :: MIT License
Classifier: Natural Language :: English
Classifier: Programming Language :: Python :: 2
Classifier: Programming Language :: Python :: 2.7
Classifier: Programming Language :: Python :: 3
Classifier: Programming Language :: Python :: 3.5
Classifier: Programming Language :: Python :: 3.6
Requires-Dist: Click (>=6.0)
